README.md
setup.py
link_shorteners/__init__.py
link_shorteners/link-shorteners.txt
link_shorteners/link_shorteners.py
link_shorteners.egg-info/PKG-INFO
link_shorteners.egg-info/SOURCES.txt
link_shorteners.egg-info/dependency_links.txt
link_shorteners.egg-info/top_level.txt