Metadata-Version: 2.1
Name: link-shorteners
Version: 1.0.5
Summary: List of all URL shorteners, such as bitly, tinyurl, shorturl, and many others.
Home-page: https://github.com/mayakyler/link-shorteners/py-link-shorteners
License: MIT
